vector_database/__init__.py
vector_database/embedding.py
vector_database-0.0.3.dist-info/LICENSE
vector_database-0.0.3.dist-info/METADATA
vector_database-0.0.3.dist-info/WHEEL
vector_database-0.0.3.dist-info/top_level.txt
vector_database-0.0.3.dist-info/RECORD
